reddit_bot/__init__.py
reddit_bot/bot.py
reddit_bot/cli.py
reddit_bot_cli-0.0.5.dist-info/LICENSE
reddit_bot_cli-0.0.5.dist-info/METADATA
reddit_bot_cli-0.0.5.dist-info/WHEEL
reddit_bot_cli-0.0.5.dist-info/entry_points.txt
reddit_bot_cli-0.0.5.dist-info/top_level.txt
reddit_bot_cli-0.0.5.dist-info/RECORD
